{
  "fundamentals": {
    "特色": "飲食店情報をインターネットで提供。飲食店からの加盟料や販促支援料が収益源。中国にも拠点",
    "連結事業": "【連結事業】ストック型サービス84、スポット型サービス7、プロモーション3、他6(2017.3)",
    "最寄り駅": " 〜 日比谷 ",
    "電話番号": "０３−３５００−９７００",
    "業種分類": "サービス業",
    "英文社名": "Ｇｕｒｕｎａｖｉ， Ｉｎｃ．",
    "代表者名": " 久保 征一郎",
    "設立年月日": "1989年10月2日",
    "市場名": "東証1部",
    "上場年月日": "2005年4月25日",
    "決算": "3月末日",
    "単元株数": "100株",
    "従業員数（単独）": "1,695人",
    "平均年齢": "35.4歳"
  },
  "profile": {},
  "special": {},
  "independent": {
    "決算期": {
      "前期": "2017年3月期",
      "2期前": "2016年3月期",
      "3期前": "2015年3月期"
    },
    "会計方式": {
      "前期": "日本方式",
      "2期前": "日本方式",
      "3期前": "日本方式"
    },
    "決算発表日": {
      "前期": "2017年5月10日",
      "2期前": "2016年5月11日",
      "3期前": "2015年5月11日"
    },
    "決算月数": {
      "前期": "12か月",
      "2期前": "12か月",
      "3期前": "12か月"
    },
    "売上高": {
      "前期": "---",
      "2期前": "34,537百万円",
      "3期前": "32,579百万円"
    },
    "営業利益": {
      "前期": "---",
      "2期前": "6,392百万円",
      "3期前": "5,079百万円"
    },
    "経常利益": {
      "前期": "---",
      "2期前": "6,432百万円",
      "3期前": "5,078百万円"
    },
    "当期利益": {
      "前期": "---",
      "2期前": "4,324百万円",
      "3期前": "3,241百万円"
    },
    "EPS（一株当たり利益）": {
      "前期": "---",
      "2期前": "89.30円",
      "3期前": "66.47円"
    },
    "調整一株当たり利益": {
      "前期": "---",
      "2期前": "88.97円",
      "3期前": "66.19円"
    },
    "1株配当": {
      "前期": "42.00円",
      "2期前": "38.00円",
      "3期前": "28.00円"
    },
    "配当区分": {
      "前期": "---",
      "2期前": "---",
      "3期前": "---"
    },
    "BPS（一株当たり純資産）": {
      "前期": "---",
      "2期前": "407.84円",
      "3期前": "350.20円"
    },
    "発行済み株式総数": {
      "前期": "48,675千株",
      "2期前": "48,675千株",
      "3期前": "48,675千株"
    },
    "総資産": {
      "前期": "---",
      "2期前": "26,848百万円",
      "3期前": "23,144百万円"
    },
    "自己資本": {
      "前期": "---",
      "2期前": "19,793百万円",
      "3期前": "16,989百万円"
    },
    "資本金": {
      "前期": "---",
      "2期前": "---",
      "3期前": "---"
    },
    "有利子負債": {
      "前期": "---",
      "2期前": "---",
      "3期前": "---"
    },
    "自己資本比率": {
      "前期": "---",
      "2期前": "73.7%",
      "3期前": "73.4%"
    },
    "ROA（総資産利益率）": {
      "前期": "---",
      "2期前": "17.30%",
      "3期前": "14.47%"
    },
    "ROE（自己資本利益率）": {
      "前期": "---",
      "2期前": "23.51%",
      "3期前": "19.80%"
    },
    "総資産経常利益率": {
      "前期": "---",
      "2期前": "25.73%",
      "3期前": "22.67%"
    }
  }
}