{
  "fundamentals": {
    "特色": "豆腐および関連製品の製造・販売で中堅。拠点置く中国地方で高シェア。業務用やおからも",
    "連結事業": "【単独事業】豆腐等製造販売100(2017.6)",
    "最寄り駅": " 〜 本郷(広島県) ",
    "電話番号": "０８４８−８６−３７８８",
    "業種分類": "食料品",
    "英文社名": "Ｙａｍａｍｉ Ｃｏｍｐａｎｙ",
    "代表者名": " 山名 清",
    "設立年月日": "2000年3月",
    "市場名": "JASDAQスタンダード",
    "上場年月日": "2016年6月17日",
    "決算": "6月末日",
    "単元株数": "100株",
    "従業員数（単独）": "154人",
    "平均年齢": "34.7歳"
  },
  "profile": {},
  "special": {},
  "independent": {
    "決算期": {
      "前期": "2017年6月期",
      "2期前": "2016年6月期",
      "3期前": "2015年6月期"
    },
    "会計方式": {
      "前期": "---",
      "2期前": "---",
      "3期前": "---"
    },
    "決算発表日": {
      "前期": "2017年8月14日",
      "2期前": "2016年8月12日",
      "3期前": "---"
    },
    "決算月数": {
      "前期": "12か月",
      "2期前": "12か月",
      "3期前": "12か月"
    },
    "売上高": {
      "前期": "9,793百万円",
      "2期前": "9,480百万円",
      "3期前": "9,084百万円"
    },
    "営業利益": {
      "前期": "942百万円",
      "2期前": "1,036百万円",
      "3期前": "430百万円"
    },
    "経常利益": {
      "前期": "940百万円",
      "2期前": "1,037百万円",
      "3期前": "419百万円"
    },
    "当期利益": {
      "前期": "630百万円",
      "2期前": "703百万円",
      "3期前": "349百万円"
    },
    "EPS（一株当たり利益）": {
      "前期": "98.86円",
      "2期前": "148.05円",
      "3期前": "164.76円"
    },
    "調整一株当たり利益": {
      "前期": "‐円",
      "2期前": "‐円",
      "3期前": "‐円"
    },
    "1株配当": {
      "前期": "20.00円",
      "2期前": "20.00円",
      "3期前": "0.00円"
    },
    "配当区分": {
      "前期": "---",
      "2期前": "記念配当を含む",
      "3期前": "---"
    },
    "BPS（一株当たり純資産）": {
      "前期": "642.61円",
      "2期前": "568.60円",
      "3期前": "307.07円"
    },
    "発行済み株式総数": {
      "前期": "6,376千株",
      "2期前": "6,376千株",
      "3期前": "---"
    },
    "総資産": {
      "前期": "8,716百万円",
      "2期前": "8,826百万円",
      "3期前": "6,625百万円"
    },
    "自己資本": {
      "前期": "4,097百万円",
      "2期前": "3,625百万円",
      "3期前": "1,707百万円"
    },
    "資本金": {
      "前期": "696百万円",
      "2期前": "696百万円",
      "3期前": "61百万円"
    },
    "有利子負債": {
      "前期": "2,970百万円",
      "2期前": "3,193百万円",
      "3期前": "3,466百万円"
    },
    "自己資本比率": {
      "前期": "47.0%",
      "2期前": "41.1%",
      "3期前": "25.8%"
    },
    "ROA（総資産利益率）": {
      "前期": "7.18%",
      "2期前": "9.10%",
      "3期前": "5.30%"
    },
    "ROE（自己資本利益率）": {
      "前期": "16.32%",
      "2期前": "26.37%",
      "3期前": "22.57%"
    },
    "総資産経常利益率": {
      "前期": "10.72%",
      "2期前": "13.42%",
      "3期前": "6.36%"
    }
  }
}