{
  "fundamentals": {
    "特色": "産業用継ぎ手最大手、半導体向けに強み。創業者が親しかったユニ・チャーム関連は保有株売却",
    "連結事業": "【連結事業】継手66、バルブ10、商品2、配管システム22(2017.3)",
    "最寄り駅": " 〜 高輪台 ",
    "電話番号": "０３−６７２１−６９８８",
    "業種分類": "金属製品",
    "英文社名": "ＩＨＡＲＡ ＳＣＩＥＮＣＥ ＣＯＲＰＯＲＡＴＩＯＮ",
    "代表者名": " 長尾 雅司",
    "設立年月日": "1947年5月21日",
    "市場名": "JASDAQスタンダード",
    "上場年月日": "1963年6月26日",
    "決算": "3月末日",
    "単元株数": "100株",
    "従業員数（単独）": "348人",
    "平均年齢": "39.3歳"
  },
  "profile": {},
  "special": {},
  "independent": {
    "決算期": {
      "前期": "2017年3月期",
      "2期前": "2016年3月期",
      "3期前": "2015年3月期"
    },
    "会計方式": {
      "前期": "日本方式",
      "2期前": "日本方式",
      "3期前": "日本方式"
    },
    "決算発表日": {
      "前期": "2017年5月12日",
      "2期前": "2016年5月12日",
      "3期前": "2015年5月14日"
    },
    "決算月数": {
      "前期": "12か月",
      "2期前": "12か月",
      "3期前": "12か月"
    },
    "売上高": {
      "前期": "13,546百万円",
      "2期前": "12,206百万円",
      "3期前": "11,155百万円"
    },
    "営業利益": {
      "前期": "2,237百万円",
      "2期前": "1,960百万円",
      "3期前": "1,630百万円"
    },
    "経常利益": {
      "前期": "2,281百万円",
      "2期前": "1,980百万円",
      "3期前": "1,701百万円"
    },
    "当期利益": {
      "前期": "1,495百万円",
      "2期前": "1,052百万円",
      "3期前": "1,352百万円"
    },
    "EPS（一株当たり利益）": {
      "前期": "146.25円",
      "2期前": "95.18円",
      "3期前": "114.87円"
    },
    "調整一株当たり利益": {
      "前期": "‐円",
      "2期前": "‐円",
      "3期前": "‐円"
    },
    "1株配当": {
      "前期": "35.00円",
      "2期前": "24.00円",
      "3期前": "22.00円"
    },
    "配当区分": {
      "前期": "記念配当を含む",
      "2期前": "---",
      "3期前": "---"
    },
    "BPS（一株当たり純資産）": {
      "前期": "1,107.44円",
      "2期前": "969.27円",
      "3期前": "889.78円"
    },
    "発行済み株式総数": {
      "前期": "14,000千株",
      "2期前": "14,000千株",
      "3期前": "14,000千株"
    },
    "総資産": {
      "前期": "15,965百万円",
      "2期前": "14,918百万円",
      "3期前": "14,072百万円"
    },
    "自己資本": {
      "前期": "11,320百万円",
      "2期前": "9,908百万円",
      "3期前": "10,474百万円"
    },
    "資本金": {
      "前期": "---",
      "2期前": "---",
      "3期前": "---"
    },
    "有利子負債": {
      "前期": "---",
      "2期前": "---",
      "3期前": "---"
    },
    "自己資本比率": {
      "前期": "70.9%",
      "2期前": "66.4%",
      "3期前": "74.4%"
    },
    "ROA（総資産利益率）": {
      "前期": "9.68%",
      "2期前": "7.26%",
      "3期前": "9.93%"
    },
    "ROE（自己資本利益率）": {
      "前期": "14.09%",
      "2期前": "10.32%",
      "3期前": "13.70%"
    },
    "総資産経常利益率": {
      "前期": "14.77%",
      "2期前": "13.66%",
      "3期前": "12.49%"
    }
  }
}