{
  "fundamentals": {
    "特色": "カフェ、レストランを直営展開。公園、水辺を含む独自出店策に強み。スイーツ事業も手掛ける",
    "連結事業": "【連結事業】レストラン88、スイーツ7、アスリート食堂5、他0(2016.7)",
    "最寄り駅": " 〜 四ツ橋 ",
    "電話番号": "０６−４３９０−６５４４",
    "業種分類": "小売業",
    "英文社名": "ＢＡＬＮＩＢＡＲＢＩ Ｃｏ．，Ｌｔｄ．",
    "代表者名": " 佐藤 裕久",
    "設立年月日": "1998年9月",
    "市場名": "マザーズ",
    "上場年月日": "2015年10月28日",
    "決算": "7月末日",
    "単元株数": "100株",
    "従業員数（単独）": "120人",
    "平均年齢": "37.1歳"
  },
  "profile": {},
  "special": {},
  "independent": {
    "決算期": {
      "前期": "2017年7月期",
      "2期前": "2016年7月期",
      "3期前": "2015年7月期"
    },
    "会計方式": {
      "前期": "日本方式",
      "2期前": "日本方式",
      "3期前": "日本方式"
    },
    "決算発表日": {
      "前期": "2017年9月12日",
      "2期前": "2016年9月13日",
      "3期前": "---"
    },
    "決算月数": {
      "前期": "12か月",
      "2期前": "12か月",
      "3期前": "12か月"
    },
    "売上高": {
      "前期": "8,919百万円",
      "2期前": "7,597百万円",
      "3期前": "5,580百万円"
    },
    "営業利益": {
      "前期": "514百万円",
      "2期前": "474百万円",
      "3期前": "367百万円"
    },
    "経常利益": {
      "前期": "501百万円",
      "2期前": "455百万円",
      "3期前": "387百万円"
    },
    "当期利益": {
      "前期": "323百万円",
      "2期前": "287百万円",
      "3期前": "227百万円"
    },
    "EPS（一株当たり利益）": {
      "前期": "77.54円",
      "2期前": "71.46円",
      "3期前": "125.12円"
    },
    "調整一株当たり利益": {
      "前期": "74.21円",
      "2期前": "68.25円",
      "3期前": "‐円"
    },
    "1株配当": {
      "前期": "15.00円",
      "2期前": "10.00円",
      "3期前": "0.00円"
    },
    "配当区分": {
      "前期": "---",
      "2期前": "---",
      "3期前": "---"
    },
    "BPS（一株当たり純資産）": {
      "前期": "475.49円",
      "2期前": "411.88円",
      "3期前": "458.68円"
    },
    "発行済み株式総数": {
      "前期": "4,185千株",
      "2期前": "4,149千株",
      "3期前": "1,819千株"
    },
    "総資産": {
      "前期": "5,934百万円",
      "2期前": "4,960百万円",
      "3期前": "3,660百万円"
    },
    "自己資本": {
      "前期": "1,990百万円",
      "2期前": "1,708百万円",
      "3期前": "834百万円"
    },
    "資本金": {
      "前期": "---",
      "2期前": "---",
      "3期前": "---"
    },
    "有利子負債": {
      "前期": "---",
      "2期前": "---",
      "3期前": "---"
    },
    "自己資本比率": {
      "前期": "33.5%",
      "2期前": "34.4%",
      "3期前": "22.8%"
    },
    "ROA（総資産利益率）": {
      "前期": "5.93%",
      "2期前": "6.66%",
      "3期前": "7.02%"
    },
    "ROE（自己資本利益率）": {
      "前期": "17.47%",
      "2期前": "22.58%",
      "3期前": "31.53%"
    },
    "総資産経常利益率": {
      "前期": "9.20%",
      "2期前": "10.56%",
      "3期前": "11.97%"
    }
  }
}