{
  "fundamentals": {
    "特色": "乳酸生菌飲料主力。女性訪問販売員による強固な販売網。医薬品も。拠点拡大で海外収益が柱に",
    "連結事業": "【連結事業】飲料・食品（国内）49(7)、飲料・食品（海外）39(25)、医薬品7(10)、他5(5)【海外】39(2017.3)",
    "最寄り駅": " 〜 新橋 ",
    "電話番号": "０３−３５７４−８９６０",
    "業種分類": "食料品",
    "英文社名": "ＹＡＫＵＬＴ ＨＯＮＳＨＡ ＣＯ．，ＬＴＤ．",
    "代表者名": " 根岸 孝成",
    "設立年月日": "1955年4月9日",
    "市場名": "東証1部",
    "上場年月日": "1980年1月",
    "決算": "3月末日",
    "単元株数": "100株",
    "従業員数（単独）": "2,860人",
    "平均年齢": "41.8歳"
  },
  "profile": {},
  "special": {},
  "independent": {
    "決算期": {
      "前期": "2017年3月期",
      "2期前": "2016年3月期",
      "3期前": "2015年3月期"
    },
    "会計方式": {
      "前期": "日本方式",
      "2期前": "日本方式",
      "3期前": "日本方式"
    },
    "決算発表日": {
      "前期": "2017年5月12日",
      "2期前": "2016年5月10日",
      "3期前": "2015年5月12日"
    },
    "決算月数": {
      "前期": "12か月",
      "2期前": "12か月",
      "3期前": "12か月"
    },
    "売上高": {
      "前期": "173,683百万円",
      "2期前": "178,821百万円",
      "3期前": "176,391百万円"
    },
    "営業利益": {
      "前期": "782百万円",
      "2期前": "1,788百万円",
      "3期前": "4,826百万円"
    },
    "経常利益": {
      "前期": "12,652百万円",
      "2期前": "12,931百万円",
      "3期前": "15,407百万円"
    },
    "当期利益": {
      "前期": "10,088百万円",
      "2期前": "9,049百万円",
      "3期前": "11,259百万円"
    },
    "EPS（一株当たり利益）": {
      "前期": "61.01円",
      "2期前": "54.72円",
      "3期前": "68.09円"
    },
    "調整一株当たり利益": {
      "前期": "‐円",
      "2期前": "‐円",
      "3期前": "‐円"
    },
    "1株配当": {
      "前期": "32.00円",
      "2期前": "50.00円",
      "3期前": "25.00円"
    },
    "配当区分": {
      "前期": "---",
      "2期前": "記念配当を含む",
      "3期前": "---"
    },
    "BPS（一株当たり純資産）": {
      "前期": "1,083.45円",
      "2期前": "1,053.44円",
      "3期前": "1,013.22円"
    },
    "発行済み株式総数": {
      "前期": "175,910千株",
      "2期前": "175,910千株",
      "3期前": "175,910千株"
    },
    "総資産": {
      "前期": "334,873百万円",
      "2期前": "328,034百万円",
      "3期前": "325,735百万円"
    },
    "自己資本": {
      "前期": "179,160百万円",
      "2期前": "174,198百万円",
      "3期前": "167,547百万円"
    },
    "資本金": {
      "前期": "---",
      "2期前": "31,117百万円",
      "3期前": "31,117百万円"
    },
    "有利子負債": {
      "前期": "---",
      "2期前": "94,150百万円",
      "3期前": "99,853百万円"
    },
    "自己資本比率": {
      "前期": "53.5%",
      "2期前": "53.1%",
      "3期前": "51.4%"
    },
    "ROA（総資産利益率）": {
      "前期": "3.04%",
      "2期前": "2.77%",
      "3期前": "3.52%"
    },
    "ROE（自己資本利益率）": {
      "前期": "5.71%",
      "2期前": "5.30%",
      "3期前": "7.20%"
    },
    "総資産経常利益率": {
      "前期": "3.82%",
      "2期前": "3.96%",
      "3期前": "4.81%"
    }
  }
}