{
  "fundamentals": {
    "特色": "発熱・計測技術の研究開発型メーカー。熱制御技術に特化。高速増殖炉関連の溶融金属に強み",
    "連結事業": "【単独事業】エネルギー関連44(13)、産業システム関連51(17)、他5(10)(2016.9)",
    "最寄り駅": " 〜 高萩 ",
    "電話番号": "０２９３−２３−６４１１",
    "業種分類": "精密機器",
    "英文社名": "ＳＵＫＥＧＡＷＡ ＥＬＥＣＴＲＩＣ ＣＯ．，ＬＴＤ．",
    "代表者名": " 小瀧 理",
    "設立年月日": "1949年2月3日",
    "市場名": "JASDAQスタンダード",
    "上場年月日": "1991年4月26日",
    "決算": "9月末日",
    "単元株数": "100株",
    "従業員数（単独）": "194人",
    "平均年齢": "44.4歳"
  },
  "profile": {},
  "special": {},
  "independent": {
    "決算期": {
      "前期": "2017年9月期",
      "2期前": "2016年9月期",
      "3期前": "2015年9月期"
    },
    "会計方式": {
      "前期": "---",
      "2期前": "---",
      "3期前": "---"
    },
    "決算発表日": {
      "前期": "2017年11月9日",
      "2期前": "2016年11月10日",
      "3期前": "2015年11月12日"
    },
    "決算月数": {
      "前期": "12か月",
      "2期前": "12か月",
      "3期前": "12か月"
    },
    "売上高": {
      "前期": "4,419百万円",
      "2期前": "4,499百万円",
      "3期前": "4,272百万円"
    },
    "営業利益": {
      "前期": "349百万円",
      "2期前": "332百万円",
      "3期前": "334百万円"
    },
    "経常利益": {
      "前期": "354百万円",
      "2期前": "319百万円",
      "3期前": "334百万円"
    },
    "当期利益": {
      "前期": "33百万円",
      "2期前": "205百万円",
      "3期前": "209百万円"
    },
    "EPS（一株当たり利益）": {
      "前期": "5.55円",
      "2期前": "33.40円",
      "3期前": "33.05円"
    },
    "調整一株当たり利益": {
      "前期": "‐円",
      "2期前": "‐円",
      "3期前": "‐円"
    },
    "1株配当": {
      "前期": "26.00円",
      "2期前": "23.00円",
      "3期前": "20.00円"
    },
    "配当区分": {
      "前期": "---",
      "2期前": "---",
      "3期前": "---"
    },
    "BPS（一株当たり純資産）": {
      "前期": "590.86円",
      "2期前": "603.64円",
      "3期前": "599.03円"
    },
    "発行済み株式総数": {
      "前期": "6,710千株",
      "2期前": "6,710千株",
      "3期前": "6,710千株"
    },
    "総資産": {
      "前期": "6,461百万円",
      "2期前": "6,331百万円",
      "3期前": "6,292百万円"
    },
    "自己資本": {
      "前期": "3,467百万円",
      "2期前": "3,662百万円",
      "3期前": "3,787百万円"
    },
    "資本金": {
      "前期": "921百万円",
      "2期前": "921百万円",
      "3期前": "921百万円"
    },
    "有利子負債": {
      "前期": "1,324百万円",
      "2期前": "1,360百万円",
      "3期前": "1,293百万円"
    },
    "自己資本比率": {
      "前期": "53.7%",
      "2期前": "57.8%",
      "3期前": "60.2%"
    },
    "ROA（総資産利益率）": {
      "前期": "0.52%",
      "2期前": "3.25%",
      "3期前": "3.31%"
    },
    "ROE（自己資本利益率）": {
      "前期": "0.93%",
      "2期前": "5.50%",
      "3期前": "5.57%"
    },
    "総資産経常利益率": {
      "前期": "5.53%",
      "2期前": "5.05%",
      "3期前": "5.29%"
    }
  }
}