{
  "fundamentals": {
    "特色": "-",
    "連結事業": "【連結事業】分譲24(5)、請負工事11(2)、小売14(1)、賃貸21(27)、管理受託12(7)、運営10(6)、仲介7(11)、他1(0)(2013.3)",
    "最寄り駅": " 〜 渋谷 ",
    "電話番号": "０３−５４５８−０６３３",
    "業種分類": "不動産業",
    "英文社名": "ＴＯＫＹＵ ＬＡＮＤ ＣＯＲＰＯＲＡＴＩＯＮ",
    "代表者名": " 金指 潔",
    "設立年月日": "1953年12月",
    "市場名": "東証1部",
    "上場年月日": "1956年4月",
    "決算": "3月末日",
    "単元株数": "1,000株",
    "従業員数（単独）": "541人",
    "平均年齢": "42.1歳"
  },
  "profile": {},
  "special": {},
  "independent": {
    "決算期": {
      "前期": "2013年3月期",
      "2期前": "2012年3月期",
      "3期前": "2011年3月期"
    },
    "会計方式": {
      "前期": "日本方式",
      "2期前": "日本方式",
      "3期前": "日本方式"
    },
    "決算発表日": {
      "前期": "2013年5月10日",
      "2期前": "2012年5月10日",
      "3期前": "2011年5月12日"
    },
    "決算月数": {
      "前期": "12か月",
      "2期前": "12か月",
      "3期前": "12か月"
    },
    "売上高": {
      "前期": "219,165百万円",
      "2期前": "187,159百万円",
      "3期前": "243,916百万円"
    },
    "営業利益": {
      "前期": "25,120百万円",
      "2期前": "15,402百万円",
      "3期前": "44,199百万円"
    },
    "経常利益": {
      "前期": "21,655百万円",
      "2期前": "12,050百万円",
      "3期前": "38,851百万円"
    },
    "当期利益": {
      "前期": "13,443百万円",
      "2期前": "4,220百万円",
      "3期前": "4,098百万円"
    },
    "EPS（一株当たり利益）": {
      "前期": "25.32円",
      "2期前": "7.95円",
      "3期前": "7.72円"
    },
    "調整一株当たり利益": {
      "前期": "‐円",
      "2期前": "‐円",
      "3期前": "‐円"
    },
    "1株配当": {
      "前期": "7.00円",
      "2期前": "7.00円",
      "3期前": "7.00円"
    },
    "配当区分": {
      "前期": "---",
      "2期前": "---",
      "3期前": "---"
    },
    "BPS（一株当たり純資産）": {
      "前期": "369.11円",
      "2期前": "333.99円",
      "3期前": "329.89円"
    },
    "発行済み株式総数": {
      "前期": "533,345千株",
      "2期前": "533,345千株",
      "3期前": "533,345千株"
    },
    "総資産": {
      "前期": "896,500百万円",
      "2期前": "889,668百万円",
      "3期前": "879,828百万円"
    },
    "自己資本": {
      "前期": "195,994百万円",
      "2期前": "177,363百万円",
      "3期前": "175,192百万円"
    },
    "資本金": {
      "前期": "57,551百万円",
      "2期前": "57,551百万円",
      "3期前": "57,551百万円"
    },
    "有利子負債": {
      "前期": "477,882百万円",
      "2期前": "489,325百万円",
      "3期前": "476,503百万円"
    },
    "自己資本比率": {
      "前期": "21.9%",
      "2期前": "19.9%",
      "3期前": "19.9%"
    },
    "ROA（総資産利益率）": {
      "前期": "1.51%",
      "2期前": "0.48%",
      "3期前": "0.48%"
    },
    "ROE（自己資本利益率）": {
      "前期": "7.20%",
      "2期前": "2.39%",
      "3期前": "2.33%"
    },
    "総資産経常利益率": {
      "前期": "2.42%",
      "2期前": "1.36%",
      "3期前": "4.54%"
    }
  }
}