{
  "fundamentals": {
    "特色": "東芝直系のプラント据え付け工事会社。海外中心に中小型発電を開拓。ＩＣカード情報系も展開",
    "連結事業": "【連結事業】発電システム62(7)、社会・産業システム38(10)【海外】24(2017.3)",
    "最寄り駅": " 〜 京急鶴見 ",
    "電話番号": "０４５−５００−７０５０",
    "業種分類": "建設業",
    "英文社名": "ＴＯＳＨＩＢＡ ＰＬＡＮＴ ＳＹＳＴＥＭＳ ＆ ＳＥＲＶＩＣＥＳ ＣＯＲＰ．",
    "代表者名": " 林 正孝",
    "設立年月日": "1938年10月3日",
    "市場名": "東証1部",
    "上場年月日": "1979年11月",
    "決算": "3月末日",
    "単元株数": "100株",
    "従業員数（単独）": "3,143人",
    "平均年齢": "45.0歳"
  },
  "profile": {},
  "special": {},
  "independent": {
    "決算期": {
      "前期": "2017年3月期",
      "2期前": "2016年3月期",
      "3期前": "2015年3月期"
    },
    "会計方式": {
      "前期": "日本方式",
      "2期前": "日本方式",
      "3期前": "日本方式"
    },
    "決算発表日": {
      "前期": "2017年5月15日",
      "2期前": "2016年5月12日",
      "3期前": "2015年7月23日"
    },
    "決算月数": {
      "前期": "12か月",
      "2期前": "12か月",
      "3期前": "12か月"
    },
    "売上高": {
      "前期": "195,040百万円",
      "2期前": "186,670百万円",
      "3期前": "194,407百万円"
    },
    "営業利益": {
      "前期": "16,827百万円",
      "2期前": "17,544百万円",
      "3期前": "15,715百万円"
    },
    "経常利益": {
      "前期": "18,348百万円",
      "2期前": "17,997百万円",
      "3期前": "16,808百万円"
    },
    "当期利益": {
      "前期": "12,606百万円",
      "2期前": "11,168百万円",
      "3期前": "9,772百万円"
    },
    "EPS（一株当たり利益）": {
      "前期": "129.41円",
      "2期前": "114.65円",
      "3期前": "100.31円"
    },
    "調整一株当たり利益": {
      "前期": "‐円",
      "2期前": "‐円",
      "3期前": "‐円"
    },
    "1株配当": {
      "前期": "38.00円",
      "2期前": "37.50円",
      "3期前": "7.50円"
    },
    "配当区分": {
      "前期": "---",
      "2期前": "特別配当を含む",
      "3期前": "---"
    },
    "BPS（一株当たり純資産）": {
      "前期": "1,362.28円",
      "2期前": "1,264.17円",
      "3期前": "1,177.18円"
    },
    "発行済み株式総数": {
      "前期": "97,656千株",
      "2期前": "97,656千株",
      "3期前": "97,656千株"
    },
    "総資産": {
      "前期": "225,978百万円",
      "2期前": "221,056百万円",
      "3期前": "212,648百万円"
    },
    "自己資本": {
      "前期": "132,704百万円",
      "2期前": "123,147百万円",
      "3期前": "114,674百万円"
    },
    "資本金": {
      "前期": "---",
      "2期前": "---",
      "3期前": "---"
    },
    "有利子負債": {
      "前期": "---",
      "2期前": "---",
      "3期前": "---"
    },
    "自己資本比率": {
      "前期": "58.7%",
      "2期前": "55.7%",
      "3期前": "53.9%"
    },
    "ROA（総資産利益率）": {
      "前期": "5.64%",
      "2期前": "5.15%",
      "3期前": "4.67%"
    },
    "ROE（自己資本利益率）": {
      "前期": "9.85%",
      "2期前": "9.39%",
      "3期前": "8.90%"
    },
    "総資産経常利益率": {
      "前期": "8.21%",
      "2期前": "8.30%",
      "3期前": "8.03%"
    }
  }
}