{
  "fundamentals": {
    "特色": "-",
    "連結事業": "【連結事業】情報・通信機器52(-2)、メカトロニクス機器23(-9)、電源・エネルギー機器20(-18)、他5(2)【海外】15(2014.3)",
    "最寄り駅": " 〜 川中島 ",
    "電話番号": "０２６−２８５−１１１１",
    "業種分類": "電気機器",
    "英文社名": "Ｎａｇａｎｏ Ｊａｐａｎ Ｒａｄｉｏ Ｃｏ．，Ｌｔｄ．",
    "代表者名": " 萩原 伸幸",
    "設立年月日": "1949年10月1日",
    "市場名": "東証2部",
    "上場年月日": "1997年10月1日",
    "決算": "3月末日",
    "単元株数": "1,000株",
    "従業員数（単独）": "762人",
    "平均年齢": "‐歳"
  },
  "profile": {},
  "special": {},
  "independent": {
    "決算期": {
      "前期": "2014年3月期",
      "2期前": "2013年3月期",
      "3期前": "2012年3月期"
    },
    "会計方式": {
      "前期": "日本方式",
      "2期前": "日本方式",
      "3期前": "日本方式"
    },
    "決算発表日": {
      "前期": "2014年5月7日",
      "2期前": "2013年5月8日",
      "3期前": "2012年5月8日"
    },
    "決算月数": {
      "前期": "12か月",
      "2期前": "12か月",
      "3期前": "12か月"
    },
    "売上高": {
      "前期": "28,705百万円",
      "2期前": "27,178百万円",
      "3期前": "27,048百万円"
    },
    "営業利益": {
      "前期": "-1,816百万円",
      "2期前": "616百万円",
      "3期前": "716百万円"
    },
    "経常利益": {
      "前期": "-1,776百万円",
      "2期前": "697百万円",
      "3期前": "655百万円"
    },
    "当期利益": {
      "前期": "-1,927百万円",
      "2期前": "217百万円",
      "3期前": "573百万円"
    },
    "EPS（一株当たり利益）": {
      "前期": "-52.94円",
      "2期前": "5.97円",
      "3期前": "15.74円"
    },
    "調整一株当たり利益": {
      "前期": "‐円",
      "2期前": "‐円",
      "3期前": "‐円"
    },
    "1株配当": {
      "前期": "0.00円",
      "2期前": "0.00円",
      "3期前": "0.00円"
    },
    "配当区分": {
      "前期": "---",
      "2期前": "---",
      "3期前": "---"
    },
    "BPS（一株当たり純資産）": {
      "前期": "85.66円",
      "2期前": "139.50円",
      "3期前": "133.18円"
    },
    "発行済み株式総数": {
      "前期": "36,420千株",
      "2期前": "36,420千株",
      "3期前": "36,420千株"
    },
    "総資産": {
      "前期": "19,719百万円",
      "2期前": "22,288百万円",
      "3期前": "22,737百万円"
    },
    "自己資本": {
      "前期": "3,118百万円",
      "2期前": "5,079百万円",
      "3期前": "4,849百万円"
    },
    "資本金": {
      "前期": "3,649百万円",
      "2期前": "3,649百万円",
      "3期前": "3,649百万円"
    },
    "有利子負債": {
      "前期": "8,640百万円",
      "2期前": "8,799百万円",
      "3期前": "8,895百万円"
    },
    "自己資本比率": {
      "前期": "15.8%",
      "2期前": "22.8%",
      "3期前": "21.3%"
    },
    "ROA（総資産利益率）": {
      "前期": "-9.17%",
      "2期前": "0.96%",
      "3期前": "2.52%"
    },
    "ROE（自己資本利益率）": {
      "前期": "-47.02%",
      "2期前": "4.37%",
      "3期前": "12.65%"
    },
    "総資産経常利益率": {
      "前期": "-8.46%",
      "2期前": "3.10%",
      "3期前": "2.88%"
    }
  }
}